changpan/README.md
changpan/__init__.py
changpan/common.py
changpan/example.cp310-win_amd64.pyd
changpan/example.cp311-win_amd64.pyd
changpan/example.cp39-win_amd64.pyd
changpan/imgProcess.py
changpan/test.py
changpan/data/data.txt
changpan/submodule/__init__.py
changpan/submodule/common.py
changpan-0.0.1.4.dist-info/METADATA
changpan-0.0.1.4.dist-info/WHEEL
changpan-0.0.1.4.dist-info/top_level.txt
changpan-0.0.1.4.dist-info/RECORD
